MANIFEST.in
account_invoice_view.xml
account_payment_demo.xml
account_payment_report.xml
account_payment_sequence.xml
account_payment_view.xml
account_payment_workflow.xml
setup.py
./__init__.py
./__openerp__.py
./account_invoice.py
./account_move_line.py
./account_payment.py
./report/__init__.py
./report/payment_order.py
./wizard/__init__.py
./wizard/account_payment_order.py
./wizard/account_payment_pay.py
./wizard/account_payment_populate_statement.py
i18n/account_payment.pot
i18n/am.po
i18n/ar.po
i18n/bg.po
i18n/bs.po
i18n/ca.po
i18n/cs.po
i18n/da.po
i18n/de.po
i18n/el.po
i18n/en_GB.po
i18n/es.po
i18n/es_AR.po
i18n/es_CL.po
i18n/es_CR.po
i18n/es_EC.po
i18n/es_MX.po
i18n/es_PY.po
i18n/es_VE.po
i18n/et.po
i18n/fa.po
i18n/fi.po
i18n/fr.po
i18n/gl.po
i18n/hi.po
i18n/hr.po
i18n/hu.po
i18n/id.po
i18n/it.po
i18n/ja.po
i18n/ko.po
i18n/lt.po
i18n/lv.po
i18n/mk.po
i18n/mn.po
i18n/nb.po
i18n/nl.po
i18n/nl_BE.po
i18n/oc.po
i18n/pl.po
i18n/pt.po
i18n/pt_BR.po
i18n/ro.po
i18n/ru.po
i18n/sl.po
i18n/sq.po
i18n/sr.po
i18n/sr@latin.po
i18n/sv.po
i18n/tlh.po
i18n/tr.po
i18n/uk.po
i18n/vi.po
i18n/zh_CN.po
i18n/zh_TW.po
images/payment_mode.jpeg
images/payment_order.jpeg
openerp_account_payment.egg-info/PKG-INFO
openerp_account_payment.egg-info/SOURCES.txt
openerp_account_payment.egg-info/dependency_links.txt
openerp_account_payment.egg-info/requires.txt
openerp_account_payment.egg-info/top_level.txt
report/order.rml
report/order.sxw
security/account_payment_security.xml
security/ir.model.access.csv
test/account_payment_demo.yml
test/account_payment_report.yml
test/cancel_payment_order.yml
test/payment_order_process.yml
wizard/account_payment_create_order_view.xml
wizard/account_payment_pay_view.xml
wizard/account_payment_populate_statement_view.xml